{
  "code": "603629",
  "name": "利通电子",
  "trade_date": "2026-07-06",
  "updated_at": "2026-07-06 23:29:03",
  "version": "1.0.0",
  "fundamentals": {
    "source": "eastmoney_value",
    "trade_date": "2026-07-06",
    "close": 172.9,
    "market_cap_yi": 453.55,
    "float_cap_yi": 446.14,
    "pe_ttm": 84.86944875,
    "pe_static": 155.01304943,
    "pb": 20.2049098,
    "ps": 12.59691088,
    "peg": 0.050057583098
  },
  "corporate": {
    "dividends": [],
    "lockups": [
      {
        "unlock_date": "2028-12-08",
        "unlock_shares": 90000.0,
        "unlock_value_yi": 0.16,
        "pct_total": 0.000343092406,
        "pct_float": 0.0003487953,
        "holder_type": "股权激励限售股份"
      },
      {
        "unlock_date": "2028-11-06",
        "unlock_shares": 645000.0,
        "unlock_value_yi": 1.12,
        "pct_total": 0.002458828911,
        "pct_float": 0.002499699648,
        "holder_type": "股权激励限售股份"
      },
      {
        "unlock_date": "2028-01-18",
        "unlock_shares": 330000.0,
        "unlock_value_yi": 0.57,
        "pct_total": 0.001258005489,
        "pct_float": 0.001278916099,
        "holder_type": "股权激励限售股份"
      }
    ],
    "earnings_forecast": null
  },
  "fund_flow": {
    "northbound": {},
    "margin": null
  },
  "index_context": {
    "trade_date": "2026-07-06",
    "benchmarks": [
      {
        "name": "上证指数",
        "code": "000001",
        "close": 4050.44,
        "change_pct": 0.17
      },
      {
        "name": "科创50",
        "code": "000688",
        "close": 2011.17,
        "change_pct": 1.8
      }
    ],
    "market_fund_flow": {
      "north_net": 0.0,
      "main_net": -861.15,
      "retail_net": 0.0
    },
    "stock_return_20d": -4.15
  },
  "cross_source": null,
  "quality_ref": {
    "status": "ok",
    "quality_score": 100.0
  },
  "limitations": [
    "partial_source_failure",
    "northbound_missing",
    "dividend_missing"
  ],
  "sources_failed": [
    "dividend",
    "earnings_forecast_20260930",
    "margin_sse",
    "northbound"
  ]
}